justforping.py
justforping-0.1.0.dist-info/LICENSE
justforping-0.1.0.dist-info/METADATA
justforping-0.1.0.dist-info/WHEEL
justforping-0.1.0.dist-info/RECORD
