Metadata-Version: 2.3
Name: justforping
Version: 0.1.0
Summary: 
Author: Ashkan Feyzollahi
Author-email: ashkanfeyzollahi@gmail.com
Requires-Python: >=3.9
Classifier: Programming Language :: Python :: 3
Classifier: Programming Language :: Python :: 3.9
Classifier: Programming Language :: Python :: 3.10
Classifier: Programming Language :: Python :: 3.11
Classifier: Programming Language :: Python :: 3.12
Classifier: Programming Language :: Python :: 3.13
